tap_gainsightpx/__init__.py
tap_gainsightpx/client.py
tap_gainsightpx/paginators.py
tap_gainsightpx/streams.py
tap_gainsightpx/tap.py
tap_gainsightpx/tests/__init__.py
tap_gainsightpx/tests/test_core.py
tap_gainsightpx-1.0.8.dist-info/METADATA
tap_gainsightpx-1.0.8.dist-info/LICENSE
tap_gainsightpx-1.0.8.dist-info/entry_points.txt
tap_gainsightpx-1.0.8.dist-info/WHEEL
tap_gainsightpx-1.0.8.dist-info/RECORD
