Metadata-Version: 2.1
Name: tap-gainsightpx
Version: 1.0.8
Summary: `tap-gainsightpx` is a Singer tap for GainsightPX, built with the Meltano Singer SDK.
Home-page: https://github.com/Widen/tap-gainsightpx
License: Apache 2.0
Keywords: ELT,GainsightPX,Meltano,Singer,REST,API,tap
Author: Josh Lloyd
Requires-Python: >=3.7.1
Classifier: License :: Other/Proprietary License
Classifier: Programming Language :: Python :: 3
Classifier: Programming Language :: Python :: 3.8
Classifier: Programming Language :: Python :: 3.9
Classifier: Programming Language :: Python :: 3.10
Classifier: Programming Language :: Python :: 3.11
Requires-Dist: requests (>=2.25.1,<3.0.0)
Requires-Dist: singer-sdk (>=0.13.0,<0.14.0)
Project-URL: Repository, https://github.com/Widen/tap-gainsightpx
